chipa_ta-0.0.1.dist-info/METADATA
chipa_ta-0.0.1.dist-info/WHEEL
chipa_ta-0.0.1.dist-info/licenses/LICENSE
chipa_ta/__init__.py
chipa_ta/chipa_ta.cp311-win_amd64.pyd
chipa_ta-0.0.1.dist-info/RECORD
