Metadata-Version: 2.4
Name: chipa_ta
Version: 0.0.1
Classifier: Programming Language :: Rust
Classifier: Programming Language :: Python :: Implementation :: CPython
Classifier: Programming Language :: Python :: Implementation :: PyPy
Classifier: Programming Language :: Python :: 3.8
Classifier: Programming Language :: Python :: 3.9
Classifier: Programming Language :: Python :: 3.10
Classifier: Programming Language :: Python :: 3.11
Classifier: Programming Language :: Python :: 3.12
Classifier: Programming Language :: Python :: 3.13
Classifier: Intended Audience :: Developers
Classifier: Topic :: Software Development :: Libraries :: Python Modules
Classifier: Operating System :: Microsoft :: Windows
Classifier: Operating System :: POSIX
Classifier: Operating System :: Unix
Classifier: Operating System :: MacOS
License-File: LICENSE
Summary: A simple rust based technical analysis library
Keywords: ta
Author-email: Rick-29 <ayfmportner@gmail.com>
License: GPL-3.0
Requires-Python: >=3.8
Project-URL: Documentation, https://github.com/ChipaDevTeam/chipa-ta
Project-URL: Homepage, https://github.com/ChipaDevTeam/chipa-ta
Project-URL: Repository, https://github.com/ChipaDevTeam/chipa-ta
